<annotation>
	<folder>Runcing</folder>
	<filename>Runcing (63).jpg</filename>
	<path>D:\Dataset\Paruh_Burung\Runcing\Runcing (63).jpg</path>
	<source>
		<database>Unknown</database>
	</source>
	<size>
		<width>933</width>
		<height>933</height>
		<depth>3</depth>
	</size>
	<segmented>0</segmented>
	<object>
		<name>Pengoyak Daging</name>
		<pose>Unspecified</pose>
		<truncated>0</truncated>
		<difficult>0</difficult>
		<bndbox>
			<xmin>648</xmin>
			<ymin>138</ymin>
			<xmax>863</xmax>
			<ymax>409</ymax>
		</bndbox>
	</object>
</annotation>
